{"id":"04-functions","level":2,"title":"Functions","category":"python","categoryLabel":"Python","points":150,"description":"Use def keyword.","objectives":["def not function"],"hints":["def name():"],"hintPenalty":20,"validationType":"python-output","files":[{"filename":"funcs.py","language":"python","editable":true,"content":"function add(a, b):\n    return a + b\n\nfunction greet(name):\n    print(f\"Hello, {name}!\")\n\nprint(add(5, 3))"}],"validation":{"checks":[{"description":"def add","astRule":{"type":"contains-string","value":"def add(a, b):"},"points":34},{"description":"def greet","astRule":{"type":"contains-string","value":"def greet(name):"},"points":33},{"description":"no function","astRule":{"type":"no-string","value":"function "},"points":33}]},"unlockRequires":["03-lists"]}
